llm_command_r.py
llm_command_r-0.3.1.dist-info/licenses/LICENSE
llm_command_r-0.3.1.dist-info/METADATA
llm_command_r-0.3.1.dist-info/WHEEL
llm_command_r-0.3.1.dist-info/entry_points.txt
llm_command_r-0.3.1.dist-info/top_level.txt
llm_command_r-0.3.1.dist-info/RECORD
