Metadata-Version: 2.4
Name: llm-command-r
Version: 0.3.1
Summary: Access the Cohere Command R family of models
Author: Simon Willison
License: Apache-2.0
Project-URL: Homepage, https://github.com/simonw/llm-command-r
Project-URL: Changelog, https://github.com/simonw/llm-command-r/releases
Project-URL: Issues, https://github.com/simonw/llm-command-r/issues
Project-URL: CI, https://github.com/simonw/llm-command-r/actions
Classifier: License :: OSI Approved :: Apache Software License
License-File: LICENSE
Requires-Dist: llm>=0.23
Requires-Dist: cohere>=5.14.0
Provides-Extra: test
Requires-Dist: pytest; extra == "test"
Requires-Dist: pytest-recording; extra == "test"
Dynamic: license-file
